tsetmc_webservice/__init__.py
tsetmc_webservice/client.py
tsetmc_webservice/pack_generator.py
tsetmc_webservice-1.0.1.dist-info/AUTHORS
tsetmc_webservice-1.0.1.dist-info/LICENSE
tsetmc_webservice-1.0.1.dist-info/METADATA
tsetmc_webservice-1.0.1.dist-info/WHEEL
tsetmc_webservice-1.0.1.dist-info/top_level.txt
tsetmc_webservice-1.0.1.dist-info/RECORD
