Metadata-Version: 2.1
Name: tsetmc-webservice
Version: 1.0.1
Summary: api to communicate with tsetmc webservice (the paid one)
Home-page: https://github.com/mahs4d/tsetmc-webservice/
Author: Mahdi Sadeghi
Author-email: mail2mahsad@gmail.com
License: UNKNOWN
Project-URL: Bug Reports, https://github.com/mahs4d/tsetmc-webservice/issues
Project-URL: Source, https://github.com/mahs4d/tsetmc-webservice/
Keywords: sample setuptools development
Platform: UNKNOWN
Classifier: Development Status :: 3 - Alpha
Classifier: Intended Audience :: Developers
Classifier: License :: OSI Approved :: MIT License
Classifier: Programming Language :: Python :: 3
Requires-Python: >=3.5
Requires-Dist: pandas
Requires-Dist: zeep
Provides-Extra: dev
